gitjirabot/__init__.py
gitjirabot/__main__.py
gitjirabot/cli.py
gitjirabot/gitjirabot.py
gitjirabot/settings.py
gitjirabot-0.1.6.dist-info/entry_points.txt
gitjirabot-0.1.6.dist-info/LICENSE
gitjirabot-0.1.6.dist-info/WHEEL
gitjirabot-0.1.6.dist-info/METADATA
gitjirabot-0.1.6.dist-info/RECORD
