Metadata-Version: 2.1
Name: gitjirabot
Version: 0.1.6
Summary: Git Jira integrations bot for automating complex tasks
Home-page: https://gitlab.com/mikeramsey/gitjirabot
License: WTFPL
Keywords: git,jira,bot,integrations,automation
Author: Michael Ramsey
Author-email: mike@hackerdise.me
Requires-Python: >=3.6,<4.0
Classifier: License :: Other/Proprietary License
Classifier: Programming Language :: Python :: 3
Classifier: Programming Language :: Python :: 3.10
Classifier: Programming Language :: Python :: 3.6
Classifier: Programming Language :: Python :: 3.7
Classifier: Programming Language :: Python :: 3.8
Classifier: Programming Language :: Python :: 3.9
Requires-Dist: atlassian-python-api (>=3.14.1,<4.0.0)
Requires-Dist: python-gitlab (>=2.10.1,<3.0.0)
Project-URL: Repository, https://gitlab.com/mikeramsey/gitjirabot
